tests/__init__.py
tests/test_core.py
tests/test_edge_cases.py
tests/test_integration.py
tests/test_loaders.py
tsdc/__init__.py
tsdc/core/__init__.py
tsdc/core/dataset.py
tsdc/core/preprocessor.py
tsdc/core/sequencer.py
tsdc/loaders/__init__.py
tsdc/loaders/base.py
tsdc/loaders/financial.py
tsdc/utils/__init__.py
tsdc/utils/splitters.py
tsdc/utils/validators.py
tsdc-0.1.0.dist-info/licenses/LICENSE
tsdc-0.1.0.dist-info/METADATA
tsdc-0.1.0.dist-info/WHEEL
tsdc-0.1.0.dist-info/top_level.txt
tsdc-0.1.0.dist-info/RECORD
