Metadata-Version: 2.4
Name: tsdc
Version: 0.1.0
Summary: A powerful library for creating time series datasets for machine learning models
Home-page: https://github.com/DeepPythonist/tsdc
Author: DeepPythonist
License: MIT
Project-URL: Homepage, https://github.com/DeepPythonist/tsdc
Project-URL: Documentation, https://github.com/DeepPythonist/tsdc/docs
Project-URL: Repository, https://github.com/DeepPythonist/tsdc
Project-URL: Bug Tracker, https://github.com/DeepPythonist/tsdc/issues
Keywords: time-series,machine-learning,lstm,dataset,deep-learning
Classifier: Development Status :: 3 - Alpha
Classifier: Intended Audience :: Developers
Classifier: Intended Audience :: Science/Research
Classifier: License :: OSI Approved :: MIT License
Classifier: Programming Language :: Python :: 3
Classifier: Programming Language :: Python :: 3.8
Classifier: Programming Language :: Python :: 3.9
Classifier: Programming Language :: Python :: 3.10
Classifier: Programming Language :: Python :: 3.11
Classifier: Programming Language :: Python :: 3.12
Classifier: Topic :: Scientific/Engineering :: Artificial Intelligence
Requires-Python: >=3.8
License-File: LICENSE
Requires-Dist: numpy>=1.21.0
Requires-Dist: pandas>=1.3.0
Requires-Dist: scikit-learn>=0.24.0
Provides-Extra: dev
Requires-Dist: pytest>=6.0.0; extra == "dev"
Requires-Dist: black>=21.0; extra == "dev"
Requires-Dist: flake8>=3.9.0; extra == "dev"
Provides-Extra: examples
Requires-Dist: yfinance>=0.1.70; extra == "examples"
Requires-Dist: matplotlib>=3.3.0; extra == "examples"
Requires-Dist: tensorflow>=2.8.0; extra == "examples"
Requires-Dist: torch>=1.10.0; extra == "examples"
Dynamic: home-page
Dynamic: license-file
Dynamic: requires-python
